mcp_time_server/__init__.py
mcp_time_server/main.py
mcp_time_servercuclsy-0.1.0.dist-info/licenses/LICENSE
mcp_time_servercuclsy-0.1.0.dist-info/METADATA
mcp_time_servercuclsy-0.1.0.dist-info/WHEEL
mcp_time_servercuclsy-0.1.0.dist-info/entry_points.txt
mcp_time_servercuclsy-0.1.0.dist-info/top_level.txt
mcp_time_servercuclsy-0.1.0.dist-info/RECORD
