Metadata-Version: 2.4
Name: mcp-time-servercuclsy
Version: 0.1.0
Summary: A simple MCP (Model Context Protocol) Server that provides a tool to get the current time with optional timezone support.
Author-email: Your Name <your.email@example.com>
License: MIT License
Classifier: Programming Language :: Python :: 3
Classifier: License :: OSI Approved :: MIT License
Classifier: Operating System :: OS Independent
Requires-Python: >=3.7
License-File: LICENSE
Requires-Dist: mcp
Requires-Dist: pytz
Dynamic: license-file
